daodb/__init__.py
daodb/brotli.py
daodb/core.py
daodb/gzip.py
daodb/jsondb.py
daodb/lz4.py
daodb/lzma.py
daodb/snappy.py
daodb-0.0.6.dist-info/LICENSE
daodb-0.0.6.dist-info/METADATA
daodb-0.0.6.dist-info/WHEEL
daodb-0.0.6.dist-info/top_level.txt
daodb-0.0.6.dist-info/RECORD
