Metadata-Version: 2.1
Name: daodb
Version: 0.0.6
Summary: Declassed Append-Only Database
Home-page: https://declassed.art/repository/daodb
Author: AXY
Author-email: axy@declassed.art
License: UNKNOWN
Platform: UNKNOWN
Classifier: Programming Language :: Python :: 3
Classifier: License :: OSI Approved :: BSD License
Classifier: Operating System :: Unix
Classifier: Intended Audience :: Developers
Classifier: Development Status :: 1 - Planning
Classifier: Topic :: Database :: Database Engines/Servers
Requires-Python: >=3.6
License-File: LICENSE
